TransportNSW/TransportNSW.py
TransportNSW/__init__.py
PyTransportNSWv2-0.4.0.dist-info/LICENSE
PyTransportNSWv2-0.4.0.dist-info/METADATA
PyTransportNSWv2-0.4.0.dist-info/WHEEL
PyTransportNSWv2-0.4.0.dist-info/top_level.txt
PyTransportNSWv2-0.4.0.dist-info/RECORD
