Metadata-Version: 2.1
Name: PyTransportNSWv2
Version: 0.4.0
Summary: Get detailed per-trip transport information from TransportNSW
Home-page: https://github.com/andystewart999/TransportNSW
Author: andystewart999
Classifier: Programming Language :: Python :: 3
Classifier: License :: OSI Approved :: MIT License
Classifier: Operating System :: OS Independent
Classifier: Intended Audience :: Developers
Classifier: Topic :: Software Development :: Libraries :: Python Modules
License-File: LICENSE
Requires-Dist: gtfs-realtime-bindings
Requires-Dist: requests
